CMakeLists.txt
LICENSE
MANIFEST.in
README.md
pyproject.toml
setup.py
imviz/__init__.py
imviz/autogui.py
imviz/common.py
imviz/dev.py
imviz/export.py
imviz/icon.py
imviz/license.py
imviz/task.py
imviz.egg-info/PKG-INFO
imviz.egg-info/SOURCES.txt
imviz.egg-info/dependency_links.txt
imviz.egg-info/not-zip-safe
imviz.egg-info/requires.txt
imviz.egg-info/top_level.txt
src/binding_helpers.cpp
src/binding_helpers.hpp
src/bindings.cpp
src/bindings_imgui.cpp
src/bindings_imgui.hpp
src/bindings_implot.cpp
src/bindings_implot.hpp
src/fa_solid_900.cpp
src/fa_solid_900.hpp
src/file_dialog.cpp
src/file_dialog.hpp
src/im_user_config.h
src/implot_ext.cpp
src/implot_ext.hpp
src/imviz.cpp
src/imviz.hpp
src/input.cpp
src/input.hpp
src/source_sans_pro.cpp
src/source_sans_pro.hpp