Metadata-Version: 2.2
Name: imviz
Version: 0.2.10
Summary: Pythonic bindings for imgui/implot
Home-page: https://github.com/joruof/imviz
Author: Jona Ruof
Author-email: jona.ruof@uni-ulm.de
License: MIT
Requires-Python: >=3.8
License-File: LICENSE
Requires-Dist: numpy
Requires-Dist: Pillow>=9.0.1
Requires-Dist: objtoolbox>=0.0.11
Requires-Dist: minireload>=0.0.9
Dynamic: author
Dynamic: author-email
Dynamic: description
Dynamic: description-content-type
Dynamic: home-page
Dynamic: license
Dynamic: requires-dist
Dynamic: requires-python
Dynamic: summary
